deca/__init__.py
deca/deca.py
deca/py.typed
deca-0.0.2.dist-info/LICENSE
deca-0.0.2.dist-info/METADATA
deca-0.0.2.dist-info/WHEEL
deca-0.0.2.dist-info/top_level.txt
deca-0.0.2.dist-info/RECORD
