Metadata-Version: 2.1
Name: deca
Version: 0.0.2
Summary: Exponential Decay library
Author-email: Jasper Spaans <j@jasper.es>
License: Copyright 2022 Jasper Spaans <j@jasper.es>        
Classifier: Development Status :: 3 - Alpha
Classifier: License :: OSI Approved :: MIT License
Classifier: Programming Language :: Python :: 3
Classifier: Programming Language :: Python :: 3.10
Classifier: Typing :: Typed
Requires-Python: >=3.10
License-File: LICENSE
Requires-Dist: attrs
